{
    "id": "camicko",
    "name": "Camicko",
    "description": "A French mini-games server for everyone",
    "addresses": ["play.camicko.fr", "minecraft.camicko.fr"],
    "primaryAddress": "play.camicko.fr",
    "minecraftVersions": ["1.8.9"],
    "primaryMinecraftVersion": "1.8.9",
    "primaryColor": "#00BFFF",
    "secondaryColor": "#0000FF",
    "primaryRegion": "EU",
    "regions": ["EU"],
    "gameTypes": ["BEDWARS", "PVP", "MINIGAMES"],
    "crossplay": false,
    "website": "https://minecraft.camicko.fr",
    "discord": "https://discord.gg/m9wwxPaFBx",
    "youtube": "camicko_mc",
    "tiktok": "camicko_"
}
