{
    "id": "netherstorm",
    "name": "Nether Storm",
    "website": "https://www.nssv.pl/",
    "store": "https://www.nssv.pl/sklep",
    "addresses": [
        "nssv.pl"
    ],
    "primaryAddress": "nssv.pl",
    "primaryColor": "#f6a61a",
    "secondaryColor": "#fff721",
    "minecraftVersions": [
        "1.8.*",
        "1.12.*",
        "1.16.*",
        "1.17.*",
        "1.18.*",
        "1.19.*"
    ],
    "primaryMinecraftVersion": "1.12.2",
    "primaryRegion": "EU",
    "regions": [
        "EU"
    ],
    "gameTypes": [
        "Minigames",
        "PvP"
    ],
    "socials": {
        "discord": "https://discord.com/invite/CZPA3aM",
        "facebook": "nsminecraft"
    }
}