{
    "id": "evolucraft",
    "name": "Evolucraft",
    "website": "https://evolucraft.fr/",
    "store": "https://store.evolucraft.fr/",
    "addresses": [
        "evolucraft.fr"
    ],
    "primaryAddress": "play.evolucraft.fr",
    "primaryColor": "#43ffb3",
    "secondaryColor": "#d9f326",
    "minecraftVersions": [
        "1.19.*"
    ],
    "primaryMinecraftVersion": "1.19.3",
    "primaryRegion": "EU",
    "regions": [
        "EU"
    ],
    "gameTypes": [
        "Survival",
        "Roleplay"
    ],
    "socials": {
        "discord": "https://discord.com/invite/evolucraft"
    }
}