{
    "id": "minehq",
    "name": "MineHQ",
    "store": "https://store.minehq.org/",
    "addresses": [
        "play.minehq.org",
        "mc.minehq.org"
    ],
    "primaryAddress": "paly.minehq.org",
    "primaryColor": "#ffa500",
    "secondaryColor": "#ffff00",
    "minecraftVersions": [
          "1.7.*", 
          "1.8", 
          "1.9", 
          "1.10", 
          "1.11", 
          "1.12",
          "1.13", 
          "1.14", 
          "1.15",
          "1.16", 
          "1.17", 
          "1.18",
          "1.19", 
          "1.20", 
          "1.21",
          "1.21.1", 
          "1.21.2", 
          "1.21.3", 
          "1.21.4"
    ],
    "primaryMinecraftVersion": "1.8.9",
    "primaryRegion": "NA",
    "regions": [
        "NA"
    ],
    "primaryLanguage": "en",
    "languages": [
        "es-EN",
        "en"
    ],
    "gameTypes": [
        "PvP",
        "UHC"
    ],
    "socials": {
        "twitter": "PlayMineHQ",
        "discord": "http://discord.minehq.org"
    }
}
