{
  "id": "bettermc",
  "name": "bettermc",
  "description": "Twoj ulubiony serwer minecraft.",
  "addresses": [
    "bettermc.eu"
  ],
  "primaryAddress": "bettermc.eu",
  "gameTypes": [
    "PvP",
    "Skyblock",
    "Survival"
  ],
  "primaryColor": "#FFAB00",
  "secondaryColor": "#FFAB00",
  "minecraftVersions": [
    "1.21.10"
  ],
  "primaryMinecraftVersion": "1.21.10",
  "languages": [
    "pl"
  ],
  "regions": [
    "EU"
  ],
  "website": "https://www.bettermc.eu",
  "store": "https://www.bettermc.eu",
  "socials": {
    "discord": "https://discord.gg/tcabTn3KA4"
  }
}
