{
    "id": "legendsnetwork",
    "name": "Legends Network",
    "store": "https://store.legends,rip/",
    "addresses": [
        "legends.rip",
    ],
    "primaryAddress": "legends.rip",
    "primaryColor": "#ff00ff",
    "secondaryColor": "#ffffff",
    "minecraftVersions": [
        "1.8.9"
        "1.7.10"
    ],
    "primaryMinecraftVersion": "1.8.9",
    "primaryRegion": "NA",
    "regions": [
        "NA"
    ],
    "gameTypes": [
        "HCF"
    ],
    "socials": {
        "discord": "https://discord.com/invite/gc9zeVVnRV"
        "twitter": "https://twitter.com/LegendsHCF"
    }
    
}
