{
    "id": "pickaxe",
    "name": "Pickaxe",
    "store": "https://store.pickaxe.net",
    "description": "Rising Prisons/Sim Minecraft Network",
    "addresses": [
        "pickaxe.net"
    ],
    "primaryAddress": "pickaxe.net",
    "primaryColor": "#315ED2",
    "secondaryColor": "#5A7BD0",
    "minecraftVersions": [
        "1.16.*",
        "1.17.*",
        "1.18.*",
        "1.19.*",
        "1.20.*",
        "1.21.*"
    ],
    "primaryMinecraftVersion": "1.20.4",
    "crossplay": true,
    "primaryRegion": "NA",
    "regions": [
        "NA",
        "EU",
        "OC",
        "AS",
        "SA"
    ],
    "primaryLanguage": "en",
    "languages": [
        "en"
    ],
    "gameTypes": [
        "Prison"
    ],
    "socials": {
        "twitter": "PickaxeNET",
        "discord": "https://www.discord.gg/pickaxe"
    }
}