{
  "id": "zenix",
  "name": "Zenix",
  "website": "https://zenix.top/",
  "store": "https://store.zenix.top/",
  "addresses": ["zenix.top"],
  "primaryAddress": "zenix.top",
  "primaryColor": "#31AFF8",
  "secondaryColor": "#1B5FC6",
  "minecraftVersions": [
    "1.8.*",
    "1.12.*",
    "1.16.*",
    "1.17.*",
    "1.18.*",
    "1.19.*"
  ],
  "primaryMinecraftVersion": "1.8.9",
  "primaryRegion": "EU",
  "regions": ["EU"],
  "gameTypes": ["Survival"],
  "socials": {
    "discord": "https://discord.gg/zenixpit"
  }
}
