{
    "id": "zelicraft",
    "name": "Zelicraft Network",
    "description": "Servidor de habla hispana, servidor de PvE y PvP. ¡Únete hoy!",
    "addresses": [
        "zelicraft.com",
        "dev.zelicraft.com",
        "potyh.es",
        "followersland.me"
    ],
    "primaryAddress": "zelicraft.com",
    "minecraftVersions": [
        "1.19.*"
    ],
    "primaryMinecraftVersion": "1.19.3",
    "primaryColor": "#8E00DD",
    "secondaryColor": "#FDD1FF",
    "primaryLanguage": "es-EN",
    "languages": [
        "es-EN"
    ],
    "primaryRegion": "NA",
    "gameTypes": [
        "PvP",
        "PvE",
        "Survival",
        "Adventure",
        "Minigames"
    ],
    "website": "https://www.zelika.es",
    "store": "https://tienda.zelicraft.com",
    "socials": {
        "twitter": "zelicraft",
        "youtube": "zelikafb",
        "discord": "https://discord.gg/zelicraft",
        "discord2": "https://discord.gg/zelika"
    }
}
