{
    "id": "catpvp",
    "name": "CatPvP",
    "store": "https://store.catpvp.xyz/",
    "addresses": [
        "catpvp.xyz"
    ],
    "primaryAddress": "catpvp.xyz",
    "primaryColor": "#00a1fb",
    "secondaryColor": "#0032b4",
    "minecraftVersions": [
        "1.16.*",
        "1.17.*",
        "1.18.*",
        "1.19.*"
    ],
    "primaryMinecraftVersion": "1.16.5",
    "primaryRegion": "AS",
    "regions": [
        "EU",
        "AS",
        "OC",
        "NA"
    ],
    "gameTypes": [
        "PvP"
    ],
    "socials": {
        "discord": "https://discord.com/invite/cYZqwmFYFF"
    }
}